django_pagetimer-0.2.0.dist-info/DESCRIPTION.rst
django_pagetimer-0.2.0.dist-info/METADATA
django_pagetimer-0.2.0.dist-info/RECORD
django_pagetimer-0.2.0.dist-info/WHEEL
django_pagetimer-0.2.0.dist-info/metadata.json
django_pagetimer-0.2.0.dist-info/top_level.txt
pagetimer/__init__.py
pagetimer/__init__.pyc
pagetimer/forms.py
pagetimer/forms.pyc
pagetimer/models.py
pagetimer/models.pyc
pagetimer/urls.py
pagetimer/urls.pyc
pagetimer/views.py
pagetimer/views.pyc
pagetimer/migrations/0001_initial.py
pagetimer/migrations/0001_initial.pyc
pagetimer/migrations/__init__.py
pagetimer/migrations/__init__.pyc
pagetimer/templates/base.html
pagetimer/templates/pagetimer/dashboard.html
pagetimer/templates/pagetimer/filter.html
pagetimer/templates/pagetimer/pagetimer.html
pagetimer/templates/pagetimer/purge.html
pagetimer/templatetags/__init__.py
pagetimer/templatetags/__init__.pyc
pagetimer/templatetags/pagetimertags.py
pagetimer/templatetags/pagetimertags.pyc
pagetimer/tests/__init__.py
pagetimer/tests/__init__.pyc
pagetimer/tests/test_templatetags.py
pagetimer/tests/test_templatetags.pyc
pagetimer/tests/test_views.py
pagetimer/tests/test_views.pyc
