Metadata-Version: 2.0
Name: django-pagetimer
Version: 0.2.0
Summary: Time user page visits
Home-page: https://github.com/ccnmtl/django-pagetimer
Author: Anders Pearson
Author-email: anders@columbia.edu
License: BSD
Platform: any
Requires-Dist: Django
Requires-Dist: six
